{"111":{
         "label_0":{
            "value":"Ausserhalb des betrachteten Bereiches",
            "pseudo":true
         },
         "label_1":{
            "value":"Z\u00fcrich",
            "pseudo":false
         },
         "label_2":{
            "value":"Glattal-Furttal",
            "pseudo":false
         },
         "label_3":{
            "value":"Limmattal",
            "pseudo":false
         },
         "label_4":{
            "value":"Knonaueramt",
            "pseudo":false
         },
         "label_5":{
            "value":"Zimmerberg",
            "pseudo":false
         },
         "label_6":{
            "value":"Pfannenstiel",
            "pseudo":false
         },
         "label_7":{
            "value":"Z\u00fcrcher Oberland",
            "pseudo":false
         },
         "label_8":{
            "value":"Winterthur",
            "pseudo":false
         },
         "label_9":{
            "value":"Weinland",
            "pseudo":false
         },
         "label_10":{
            "value":"Z\u00fcrcher Unterland",
            "pseudo":false
         },
         "label_11":{
            "value":"Bern",
            "pseudo":false
         },
         "label_12":{
            "value":"Erlach-Seeland",
            "pseudo":false
         },
         "label_13":{
            "value":"Biel\/Bienne",
            "pseudo":false
         },
         "label_14":{
            "value":"Jura bernois",
            "pseudo":false
         },
         "label_15":{
            "value":"Oberaargau",
            "pseudo":false
         },
         "label_16":{
            "value":"Burgdorf",
            "pseudo":false
         },
         "label_17":{
            "value":"Oberes Emmental",
            "pseudo":false
         },
         "label_18":{
            "value":"Aaretal",
            "pseudo":false
         },
         "label_19":{
            "value":"Schwarzwasser",
            "pseudo":false
         },
         "label_20":{
            "value":"Thun",
            "pseudo":false
         },
         "label_21":{
            "value":"Saanen-Obersimmental",
            "pseudo":false
         },
         "label_22":{
            "value":"Kandertal",
            "pseudo":false
         },
         "label_23":{
            "value":"Oberland-Ost",
            "pseudo":false
         },
         "label_24":{
            "value":"Grenchen",
            "pseudo":false
         },
         "label_25":{
            "value":"Laufental",
            "pseudo":false
         },
         "label_26":{
            "value":"Luzern",
            "pseudo":false
         },
         "label_27":{
            "value":"Sursee-Seetal",
            "pseudo":false
         },
         "label_28":{
            "value":"Willisau",
            "pseudo":false
         },
         "label_29":{
            "value":"Entlebuch",
            "pseudo":false
         },
         "label_30":{
            "value":"Uri",
            "pseudo":false
         },
         "label_31":{
            "value":"Innerschwyz",
            "pseudo":false
         },
         "label_32":{
            "value":"Einsiedeln",
            "pseudo":false
         },
         "label_33":{
            "value":"March",
            "pseudo":false
         },
         "label_34":{
            "value":"Sarneraatal",
            "pseudo":false
         },
         "label_35":{
            "value":"Nidwalden",
            "pseudo":false
         },
         "label_36":{
            "value":"Glarner Unterland",
            "pseudo":false
         },
         "label_37":{
            "value":"Glarner Hinterland",
            "pseudo":false
         },
         "label_38":{
            "value":"Zug",
            "pseudo":false
         },
         "label_39":{
            "value":"La Sarine",
            "pseudo":false
         },
         "label_40":{
            "value":"La Gruy\u00e8re",
            "pseudo":false
         },
         "label_41":{
            "value":"Sense",
            "pseudo":false
         },
         "label_42":{
            "value":"Murten\/Morat",
            "pseudo":false
         },
         "label_43":{
            "value":"Gl\u00e2ne-Veveyse",
            "pseudo":false
         },
         "label_44":{
            "value":"Olten",
            "pseudo":false
         },
         "label_45":{
            "value":"Thal",
            "pseudo":false
         },
         "label_46":{
            "value":"Solothurn",
            "pseudo":false
         },
         "label_47":{
            "value":"Basel-Stadt",
            "pseudo":false
         },
         "label_48":{
            "value":"Unteres Baselbiet",
            "pseudo":false
         },
         "label_49":{
            "value":"Oberes Baselbiet",
            "pseudo":false
         },
         "label_50":{
            "value":"Schaffhausen",
            "pseudo":false
         },
         "label_51":{
            "value":"Appenzell A.Rh.",
            "pseudo":false
         },
         "label_52":{
            "value":"Appenzell I.Rh.",
            "pseudo":false
         },
         "label_53":{
            "value":"St.Gallen",
            "pseudo":false
         },
         "label_54":{
            "value":"Rheintal",
            "pseudo":false
         },
         "label_55":{
            "value":"Werdenberg",
            "pseudo":false
         },
         "label_56":{
            "value":"Sarganserland",
            "pseudo":false
         },
         "label_57":{
            "value":"Linthgebiet",
            "pseudo":false
         },
         "label_58":{
            "value":"Toggenburg",
            "pseudo":false
         },
         "label_59":{
            "value":"Wil",
            "pseudo":false
         },
         "label_60":{
            "value":"Chur",
            "pseudo":false
         },
         "label_61":{
            "value":"Pr\u00e4ttigau",
            "pseudo":false
         },
         "label_62":{
            "value":"Davos",
            "pseudo":false
         },
         "label_63":{
            "value":"Schanfigg",
            "pseudo":false
         },
         "label_64":{
            "value":"Mittelb\u00fcnden",
            "pseudo":false
         },
         "label_65":{
            "value":"Viamala",
            "pseudo":false
         },
         "label_66":{
            "value":"Surselva",
            "pseudo":false
         },
         "label_67":{
            "value":"Engiadina Bassa",
            "pseudo":false
         },
         "label_68":{
            "value":"Oberengadin",
            "pseudo":false
         },
         "label_69":{
            "value":"Mesolcina",
            "pseudo":false
         },
         "label_70":{
            "value":"Aarau",
            "pseudo":false
         },
         "label_71":{
            "value":"Brugg-Zurzach",
            "pseudo":false
         },
         "label_72":{
            "value":"Baden",
            "pseudo":false
         },
         "label_73":{
            "value":"Mutschellen",
            "pseudo":false
         },
         "label_74":{
            "value":"Freiamt",
            "pseudo":false
         },
         "label_75":{
            "value":"Fricktal",
            "pseudo":false
         },
         "label_76":{
            "value":"Thurtal",
            "pseudo":false
         },
         "label_77":{
            "value":"Untersee",
            "pseudo":false
         },
         "label_78":{
            "value":"Oberthurgau",
            "pseudo":false
         },
         "label_79":{
            "value":"Tre Valli",
            "pseudo":false
         },
         "label_80":{
            "value":"Locarno",
            "pseudo":false
         },
         "label_81":{
            "value":"Bellinzona",
            "pseudo":false
         },
         "label_82":{
            "value":"Lugano",
            "pseudo":false
         },
         "label_83":{
            "value":"Mendrisio",
            "pseudo":false
         },
         "label_84":{
            "value":"Lausanne",
            "pseudo":false
         },
         "label_85":{
            "value":"Morges",
            "pseudo":false
         },
         "label_86":{
            "value":"Nyon",
            "pseudo":false
         },
         "label_87":{
            "value":"Vevey",
            "pseudo":false
         },
         "label_88":{
            "value":"Aigle",
            "pseudo":false
         },
         "label_89":{
            "value":"Pays d'Enhaut",
            "pseudo":false
         },
         "label_90":{
            "value":"Gros-de-Vaud",
            "pseudo":false
         },
         "label_91":{
            "value":"Yverdon",
            "pseudo":false
         },
         "label_92":{
            "value":"La Vall\u00e9e",
            "pseudo":false
         },
         "label_93":{
            "value":"La Broye",
            "pseudo":false
         },
         "label_94":{
            "value":"Goms",
            "pseudo":false
         },
         "label_95":{
            "value":"Brig",
            "pseudo":false
         },
         "label_96":{
            "value":"Visp",
            "pseudo":false
         },
         "label_97":{
            "value":"Leuk",
            "pseudo":false
         },
         "label_98":{
            "value":"Sierre",
            "pseudo":false
         },
         "label_99":{
            "value":"Sion",
            "pseudo":false
         },
         "label_100":{
            "value":"Martigny",
            "pseudo":false
         },
         "label_101":{
            "value":"Monthey",
            "pseudo":false
         },
         "label_102":{
            "value":"Neuch\u00e2tel",
            "pseudo":false
         },
         "label_103":{
            "value":"La Chaux-de-Fonds",
            "pseudo":false
         },
         "label_104":{
            "value":"Val-de-Travers",
            "pseudo":false
         },
         "label_105":{
            "value":"Gen\u00e8ve",
            "pseudo":false
         },
         "label_106":{
            "value":"Jura",
            "pseudo":false
         }
      }
   }